j5r_mc/__init__.py
j5r_mc/mc.py
j5r_mc-0.3.dist-info/METADATA
j5r_mc-0.3.dist-info/WHEEL
j5r_mc-0.3.dist-info/top_level.txt
j5r_mc-0.3.dist-info/RECORD
