Metadata-Version: 2.1
Name: j5r-mc
Version: 0.3
Summary: Markov Chain manager.
Home-page: UNKNOWN
Author: Junior R. Ribeiro
Author-email: juniorribeiro2013@gmail.com
License: Free for non-commercial use
Keywords: Markov,Chain,probability,stochastic
Platform: UNKNOWN
Classifier: Development Status :: 5 - Production/Stable
Classifier: Intended Audience :: Developers
Classifier: Topic :: Artistic Software
Classifier: License :: Free for non-commercial use
Classifier: Programming Language :: Python :: 3.6
Classifier: Programming Language :: Python :: 3.7
Requires-Dist: sh (>=1.11)
